idemptx/__init__.py
idemptx/backend/__init__.py
idemptx/backend/base.py
idemptx/backend/memory.py
idemptx/backend/redis.py
idemptx/decorator.py
idemptx/exceptions.py
idemptx-0.2.2.dist-info/LICENSE
idemptx-0.2.2.dist-info/METADATA
idemptx-0.2.2.dist-info/WHEEL
idemptx-0.2.2.dist-info/RECORD
