Metadata-Version: 2.1
Name: idemptx
Version: 0.2.2
Summary: Idempotency decorator for FastAPI
Home-page: https://github.com/pypy-riley/idemptx
License: MIT
Keywords: fastapi,idempotency,decorator,redis,cache
Author: pypy-riley
Author-email: pypy.riley@gmail.com
Requires-Python: >=3.9,<4.0
Classifier: License :: OSI Approved :: MIT License
Classifier: Programming Language :: Python :: 3
Classifier: Programming Language :: Python :: 3.9
Classifier: Programming Language :: Python :: 3.10
Classifier: Programming Language :: Python :: 3.11
Classifier: Programming Language :: Python :: 3.12
Requires-Dist: fastapi
Requires-Dist: pydantic (>=2.0,<3.0)
Requires-Dist: redis (>=4.2,<6.0)
Project-URL: Documentation, https://github.com/pypy-riley/idemptx#readme
Project-URL: Repository, https://github.com/pypy-riley/idemptx
